rtl/smart_home_controller.v
// ============================================================
// Project     : Smart Home Automation Controller on FPGA
// File        : smart_home_controller.v
// Author      : Seshuu
// Description : Top-level RTL module for Smart Home Automation
//               Implements FSM-based appliance control logic
//               with sensor inputs, manual override, security
//               alarm, and energy-saving mode.
// ============================================================

module smart_home_controller (
    // ---- Clock and Reset ----
    input  wire        clk,           // System clock
    input  wire        rst_n,         // Active-low synchronous reset

    // ---- Sensor Inputs ----
    input  wire        light_sensor,  // 1 = Low light detected
    input  wire        motion_sensor, // 1 = Motion detected
    input  wire        temp_high,     // 1 = Temperature above threshold
    input  wire        door_sensor,   // 1 = Door is OPEN
    input  wire        security_mode, // 1 = Security mode enabled

    // ---- Manual Override Inputs ----
    input  wire        manual_light,  // Manual: force light ON
    input  wire        manual_fan,    // Manual: force fan ON
    input  wire        manual_ac,     // Manual: force AC ON

    // ---- Appliance Outputs ----
    output reg         light_ctrl,    // 1 = Room light ON
    output reg         fan_ctrl,      // 1 = Fan ON
    output reg         ac_ctrl,       // 1 = AC ON
    output reg         door_alert,    // 1 = Door alert active
    output reg         alarm_ctrl,    // 1 = Security alarm ON
    output reg         energy_save,   // 1 = Energy-saving mode active

    // ---- Status Output ----
    output reg [2:0]   fsm_state      // Current FSM state (for debug/display)
);

    // ============================================================
    // FSM State Encoding
    // ============================================================
    localparam IDLE         = 3'd0;  // System idle, all OFF
    localparam AUTO_CTRL    = 3'd1;  // Automated sensor-based control
    localparam SECURITY     = 3'd2;  // Security mode: alarm check
    localparam ENERGY_SAVE  = 3'd3;  // Energy-saving mode
    localparam MANUAL_OVR   = 3'd4;  // Manual override active
    localparam ALARM_STATE  = 3'd5;  // Alarm triggered

    // ============================================================
    // Internal Registers
    // ============================================================
    reg [2:0] current_state, next_state;

    // No-motion counter for energy-saving (8-bit = max 255 clock cycles)
    // In real design, scale to minutes using a clock divider
    reg [7:0] no_motion_counter;
    localparam NO_MOTION_THRESHOLD = 8'd200; // threshold for energy save trigger

    // ============================================================
    // STATE REGISTER (Sequential - clock edge)
    // ============================================================
    always @(posedge clk or negedge rst_n) begin
        if (!rst_n)
            current_state <= IDLE;
        else
            current_state <= next_state;
    end

    // ============================================================
    // NO-MOTION COUNTER (Sequential)
    // ============================================================
    always @(posedge clk or negedge rst_n) begin
        if (!rst_n)
            no_motion_counter <= 8'd0;
        else if (motion_sensor)
            no_motion_counter <= 8'd0;       // Reset counter on motion
        else if (no_motion_counter < NO_MOTION_THRESHOLD)
            no_motion_counter <= no_motion_counter + 1;
    end

    // ============================================================
    // NEXT STATE LOGIC (Combinational)
    // Priority: Manual > Alarm > Security > Auto > Energy Save > Idle
    // ============================================================
    always @(*) begin
        // Default: stay in current state
        next_state = current_state;

        case (current_state)

            IDLE: begin
                if (manual_light || manual_fan || manual_ac)
                    next_state = MANUAL_OVR;
                else if (security_mode && door_sensor)
                    next_state = ALARM_STATE;
                else if (security_mode)
                    next_state = SECURITY;
                else if (motion_sensor || temp_high)
                    next_state = AUTO_CTRL;
                else
                    next_state = IDLE;
            end

            AUTO_CTRL: begin
                if (manual_light || manual_fan || manual_ac)
                    next_state = MANUAL_OVR;
                else if (security_mode && door_sensor)
                    next_state = ALARM_STATE;
                else if (security_mode)
                    next_state = SECURITY;
                else if (no_motion_counter >= NO_MOTION_THRESHOLD)
                    next_state = ENERGY_SAVE;
                else if (!motion_sensor && !temp_high)
                    next_state = IDLE;
                else
                    next_state = AUTO_CTRL;
            end

            SECURITY: begin
                if (door_sensor)
                    next_state = ALARM_STATE;
                else if (manual_light || manual_fan || manual_ac)
                    next_state = MANUAL_OVR;
                else if (!security_mode)
                    next_state = IDLE;
                else
                    next_state = SECURITY;
            end

            ALARM_STATE: begin
                // Alarm stays until security mode is turned OFF
                if (!security_mode)
                    next_state = IDLE;
                else
                    next_state = ALARM_STATE;
            end

            ENERGY_SAVE: begin
                if (manual_light || manual_fan || manual_ac)
                    next_state = MANUAL_OVR;
                else if (security_mode && door_sensor)
                    next_state = ALARM_STATE;
                else if (motion_sensor)
                    next_state = AUTO_CTRL;
                else
                    next_state = ENERGY_SAVE;
            end

            MANUAL_OVR: begin
                // Leave manual mode only when all manual switches are OFF
                if (!manual_light && !manual_fan && !manual_ac) begin
                    if (security_mode && door_sensor)
                        next_state = ALARM_STATE;
                    else if (motion_sensor || temp_high)
                        next_state = AUTO_CTRL;
                    else
                        next_state = IDLE;
                end
                else
                    next_state = MANUAL_OVR;
            end

            default: next_state = IDLE;
        endcase
    end

    // ============================================================
    // OUTPUT LOGIC (Sequential - registered outputs for stability)
    // ============================================================
    always @(posedge clk or negedge rst_n) begin
        if (!rst_n) begin
            light_ctrl  <= 1'b0;
            fan_ctrl    <= 1'b0;
            ac_ctrl     <= 1'b0;
            door_alert  <= 1'b0;
            alarm_ctrl  <= 1'b0;
            energy_save <= 1'b0;
            fsm_state   <= IDLE;
        end
        else begin
            // Default: all OFF
            light_ctrl  <= 1'b0;
            fan_ctrl    <= 1'b0;
            ac_ctrl     <= 1'b0;
            door_alert  <= 1'b0;
            alarm_ctrl  <= 1'b0;
            energy_save <= 1'b0;
            fsm_state   <= next_state;

            case (next_state)

                IDLE: begin
                    // All outputs OFF; only door alert if door open
                    door_alert  <= door_sensor;
                end

                AUTO_CTRL: begin
                    // Light: turn ON if motion detected AND it's dark
                    light_ctrl  <= motion_sensor & light_sensor;
                    // Fan: turn ON if temperature is high
                    fan_ctrl    <= temp_high;
                    // AC: turn ON if temperature is very high (temp_high sustained)
                    ac_ctrl     <= temp_high & motion_sensor;
                    door_alert  <= door_sensor;
                end

                SECURITY: begin
                    // Security mode: monitor door, light stays dim
                    door_alert  <= door_sensor;
                    light_ctrl  <= 1'b1; // Keep hallway light ON in security mode
                end

                ALARM_STATE: begin
                    alarm_ctrl  <= 1'b1; // Alarm ON
                    light_ctrl  <= 1'b1; // All lights ON
                    door_alert  <= 1'b1; // Door alert ON
                end

                ENERGY_SAVE: begin
                    energy_save <= 1'b1; // Indicate energy save mode
                    // All appliances OFF to save power
                    // Only door alert remains if door is open
                    door_alert  <= door_sensor;
                end

                MANUAL_OVR: begin
                    // Manual switches directly drive outputs
                    light_ctrl  <= manual_light;
                    fan_ctrl    <= manual_fan;
                    ac_ctrl     <= manual_ac;
                    door_alert  <= door_sensor;
                end

                default: begin
                    // Safe default: all OFF
                end
            endcase
        end
    end

endmodule

tb/tb_smart_home_controller.v
// ============================================================
// Project     : Smart Home Automation Controller on FPGA
// File        : tb_smart_home_controller.v
// Author      : Seshuu
// Description : Comprehensive testbench covering all scenarios:
//               Reset, Auto control, Security alarm, Manual
//               override, Energy-saving mode, Priority logic.
// ============================================================

`timescale 1ns / 1ps

module tb_smart_home_controller;

    // ---- DUT Port Connections ----
    reg        clk;
    reg        rst_n;
    reg        light_sensor;
    reg        motion_sensor;
    reg        temp_high;
    reg        door_sensor;
    reg        security_mode;
    reg        manual_light;
    reg        manual_fan;
    reg        manual_ac;

    wire       light_ctrl;
    wire       fan_ctrl;
    wire       ac_ctrl;
    wire       door_alert;
    wire       alarm_ctrl;
    wire       energy_save;
    wire [2:0] fsm_state;

    // ---- FSM State Names (for readability in log) ----
    reg [127:0] state_name;
    always @(*) begin
        case (fsm_state)
            3'd0: state_name = "IDLE       ";
            3'd1: state_name = "AUTO_CTRL  ";
            3'd2: state_name = "SECURITY   ";
            3'd3: state_name = "ENERGY_SAVE";
            3'd4: state_name = "MANUAL_OVR ";
            3'd5: state_name = "ALARM_STATE";
            default: state_name = "UNKNOWN    ";
        endcase
    end

    // ============================================================
    // DUT Instantiation
    // ============================================================
    smart_home_controller DUT (
        .clk          (clk),
        .rst_n        (rst_n),
        .light_sensor (light_sensor),
        .motion_sensor(motion_sensor),
        .temp_high    (temp_high),
        .door_sensor  (door_sensor),
        .security_mode(security_mode),
        .manual_light (manual_light),
        .manual_fan   (manual_fan),
        .manual_ac    (manual_ac),
        .light_ctrl   (light_ctrl),
        .fan_ctrl     (fan_ctrl),
        .ac_ctrl      (ac_ctrl),
        .door_alert   (door_alert),
        .alarm_ctrl   (alarm_ctrl),
        .energy_save  (energy_save),
        .fsm_state    (fsm_state)
    );

    // ============================================================
    // Clock Generation: 10 ns period = 100 MHz
    // ============================================================
    initial clk = 0;
    always #5 clk = ~clk;

    // ============================================================
    // Waveform Dump (for GTKWave / ModelSim)
    // ============================================================
    initial begin
        $dumpfile("waveforms/smart_home_tb.vcd");
        $dumpvars(0, tb_smart_home_controller);
    end

    // ============================================================
    // Display Header
    // ============================================================
    initial begin
        $display("==========================================================");
        $display("  Smart Home Automation Controller - Testbench Started");
        $display("==========================================================");
        $display("Time | State       | Light Fan AC | DoorAlrt Alarm EnrSv");
        $display("----------------------------------------------------------");
    end

    // ============================================================
    // Monitor: print output on every change
    // ============================================================
    always @(posedge clk) begin
        $display("%4t | %s | %b     %b   %b  |   %b        %b      %b",
            $time, state_name,
            light_ctrl, fan_ctrl, ac_ctrl,
            door_alert, alarm_ctrl, energy_save);
    end

    // ============================================================
    // Task: Apply inputs and wait N clock cycles
    // ============================================================
    task apply_inputs;
        input ls, ms, th, ds, sm, ml, mf, ma;
        input integer wait_cycles;
        begin
            light_sensor  = ls;
            motion_sensor = ms;
            temp_high     = th;
            door_sensor   = ds;
            security_mode = sm;
            manual_light  = ml;
            manual_fan    = mf;
            manual_ac     = ma;
            repeat(wait_cycles) @(posedge clk);
        end
    endtask

    // ============================================================
    // MAIN TEST SEQUENCE
    // ============================================================
    initial begin

        // --------------------------------------------------
        // TEST 1: Reset Condition
        // --------------------------------------------------
        $display("\n--- TEST 1: Reset Condition ---");
        rst_n = 0;
        apply_inputs(0, 0, 0, 0, 0, 0, 0, 0, 5);
        rst_n = 1;
        @(posedge clk); #1;
        $display("RESET released. Expecting IDLE state, all outputs OFF.");

        // --------------------------------------------------
        // TEST 2: IDLE - No sensor, no motion
        // --------------------------------------------------
        $display("\n--- TEST 2: IDLE State (No Motion, No Temp) ---");
        apply_inputs(0, 0, 0, 0, 0, 0, 0, 0, 5);
        $display("Expected: IDLE, all outputs OFF.");

        // --------------------------------------------------
        // TEST 3: Motion + Low Light → AUTO_CTRL → Light ON
        // --------------------------------------------------
        $display("\n--- TEST 3: Motion + Low Light → Light ON ---");
        apply_inputs(1, 1, 0, 0, 0, 0, 0, 0, 5);
        $display("Expected: AUTO_CTRL, light_ctrl=1, fan=0, ac=0.");

        // --------------------------------------------------
        // TEST 4: High Temperature → Fan + AC ON
        // --------------------------------------------------
        $display("\n--- TEST 4: High Temp + Motion → Fan + AC ON ---");
        apply_inputs(0, 1, 1, 0, 0, 0, 0, 0, 5);
        $display("Expected: AUTO_CTRL, fan=1, ac=1, light=0.");

        // --------------------------------------------------
        // TEST 5: Motion + Low Light + High Temp → All ON
        // --------------------------------------------------
        $display("\n--- TEST 5: Motion + Low Light + High Temp → Light+Fan+AC ---");
        apply_inputs(1, 1, 1, 0, 0, 0, 0, 0, 5);
        $display("Expected: AUTO_CTRL, light=1, fan=1, ac=1.");

        // --------------------------------------------------
        // TEST 6: Security Mode ON, Door Closed
        // --------------------------------------------------
        $display("\n--- TEST 6: Security Mode ON, Door Closed → SECURITY State ---");
        apply_inputs(0, 0, 0, 0, 1, 0, 0, 0, 5);
        $display("Expected: SECURITY state, light=1, alarm=0.");

        // --------------------------------------------------
        // TEST 7: Security Mode + Door Opens → ALARM
        // --------------------------------------------------
        $display("\n--- TEST 7: Security Mode + Door Opens → ALARM ---");
        apply_inputs(0, 0, 0, 1, 1, 0, 0, 0, 5);
        $display("Expected: ALARM_STATE, alarm=1, light=1, door_alert=1.");

        // --------------------------------------------------
        // TEST 8: Security Mode OFF → Alarm Clears
        // --------------------------------------------------
        $display("\n--- TEST 8: Security Mode Disabled → Returns to IDLE ---");
        apply_inputs(0, 0, 0, 0, 0, 0, 0, 0, 5);
        $display("Expected: IDLE, alarm=0.");

        // --------------------------------------------------
        // TEST 9: Manual Override - Light ON manually
        // --------------------------------------------------
        $display("\n--- TEST 9: Manual Override → Light ON ---");
        apply_inputs(0, 0, 0, 0, 0, 1, 0, 0, 5);
        $display("Expected: MANUAL_OVR, light=1, fan=0, ac=0.");

        // --------------------------------------------------
        // TEST 10: Manual Override - Fan + AC manually
        // --------------------------------------------------
        $display("\n--- TEST 10: Manual Override → Fan + AC ON ---");
        apply_inputs(0, 0, 0, 0, 0, 0, 1, 1, 5);
        $display("Expected: MANUAL_OVR, fan=1, ac=1, light=0.");

        // --------------------------------------------------
        // TEST 11: Manual Override - All three ON simultaneously
        // --------------------------------------------------
        $display("\n--- TEST 11: Manual Override → All ON ---");
        apply_inputs(0, 0, 0, 0, 0, 1, 1, 1, 5);
        $display("Expected: MANUAL_OVR, light=1, fan=1, ac=1.");

        // --------------------------------------------------
        // TEST 12: Manual Override cleared → back to IDLE
        // --------------------------------------------------
        $display("\n--- TEST 12: Manual Override Cleared → IDLE ---");
        apply_inputs(0, 0, 0, 0, 0, 0, 0, 0, 5);
        $display("Expected: IDLE, all outputs OFF.");

        // --------------------------------------------------
        // TEST 13: Energy Saving Mode (no motion for 200+ cycles)
        // --------------------------------------------------
        $display("\n--- TEST 13: Energy Saving (no motion) ---");
        // Step 1: Enter AUTO_CTRL with motion + temp
        apply_inputs(1, 1, 1, 0, 0, 0, 0, 0, 3);
        // Step 2: Remove motion but keep temp_high to stay in AUTO_CTRL
        //         while counter counts up to 200
        apply_inputs(0, 0, 1, 0, 0, 0, 0, 0, 210);
        $display("Expected: ENERGY_SAVE, energy_save=1, all appliances OFF.");

        // --------------------------------------------------
        // TEST 14: Motion detected again → exits Energy Save
        // --------------------------------------------------
        $display("\n--- TEST 14: Motion Returns → Exit Energy Save ---");
        apply_inputs(1, 1, 0, 0, 0, 0, 0, 0, 5);
        $display("Expected: AUTO_CTRL, light=1, energy_save=0.");

        // --------------------------------------------------
        // TEST 15: Priority Check - Manual overrides security alarm
        // --------------------------------------------------
        $display("\n--- TEST 15: Manual Priority Over Security Mode ---");
        apply_inputs(0, 0, 0, 1, 1, 1, 0, 0, 5);
        $display("Expected: MANUAL_OVR (manual takes priority), light=1.");

        // --------------------------------------------------
        // TEST 16: Door alert in IDLE (door open, no security)
        // --------------------------------------------------
        $display("\n--- TEST 16: Door Open (No Security) → door_alert only ---");
        apply_inputs(0, 0, 0, 1, 0, 0, 0, 0, 5);
        $display("Expected: IDLE, door_alert=1, alarm=0.");

        // --------------------------------------------------
        // DONE
        // --------------------------------------------------
        $display("\n==========================================================");
        $display("  All Tests Completed Successfully!");
        $display("==========================================================");
        $finish;
    end

endmodule

waveforms/smart_home_tb.vcd
$date
	Thu Jun 18 08:32:24 2026
$end
$version
	Icarus Verilog
$end
$timescale
	1ps
$end
$scope module tb_smart_home_controller $end
$var wire 1 ! light_ctrl $end
$var wire 3 " fsm_state [2:0] $end
$var wire 1 # fan_ctrl $end
$var wire 1 $ energy_save $end
$var wire 1 % door_alert $end
$var wire 1 & alarm_ctrl $end
$var wire 1 ' ac_ctrl $end
$var reg 1 ( clk $end
$var reg 1 ) door_sensor $end
$var reg 1 * light_sensor $end
$var reg 1 + manual_ac $end
$var reg 1 , manual_fan $end
$var reg 1 - manual_light $end
$var reg 1 . motion_sensor $end
$var reg 1 / rst_n $end
$var reg 1 0 security_mode $end
$var reg 128 1 state_name [127:0] $end
$var reg 1 2 temp_high $end
$scope module DUT $end
$var wire 1 ( clk $end
$var wire 1 ) door_sensor $end
$var wire 1 * light_sensor $end
$var wire 1 + manual_ac $end
$var wire 1 , manual_fan $end
$var wire 1 - manual_light $end
$var wire 1 . motion_sensor $end
$var wire 1 / rst_n $end
$var wire 1 0 security_mode $end
$var wire 1 2 temp_high $end
$var parameter 3 3 ALARM_STATE $end
$var parameter 3 4 AUTO_CTRL $end
$var parameter 3 5 ENERGY_SAVE $end
$var parameter 3 6 IDLE $end
$var parameter 3 7 MANUAL_OVR $end
$var parameter 8 8 NO_MOTION_THRESHOLD $end
$var parameter 3 9 SECURITY $end
$var reg 1 ' ac_ctrl $end
$var reg 1 & alarm_ctrl $end
$var reg 3 : current_state [2:0] $end
$var reg 1 % door_alert $end
$var reg 1 $ energy_save $end
$var reg 1 # fan_ctrl $end
$var reg 3 ; fsm_state [2:0] $end
$var reg 1 ! light_ctrl $end
$var reg 3 < next_state [2:0] $end
$var reg 8 = no_motion_counter [7:0] $end
$upscope $end
$scope task apply_inputs $end
$var reg 1 > ds $end
$var reg 1 ? ls $end
$var reg 1 @ ma $end
$var reg 1 A mf $end
$var reg 1 B ml $end
$var reg 1 C ms $end
$var reg 1 D sm $end
$var reg 1 E th $end
$var integer 32 F wait_cycles [31:0] $end
$upscope $end
$upscope $end
$enddefinitions $end
$comment Show the parameter values. $end
$dumpall
b10 9
b11001000 8
b100 7
b0 6
b11 5
b1 4
b101 3
$end
#0
$dumpvars
b101 F
0E
0D
0C
0B
0A
0@
0?
0>
b0 =
b0 <
b0 ;
b0 :
02
b100100101000100010011000100010100100000001000000010000000100000001000000010000000100000 1
00
0/
0.
0-
0,
0+
0*
0)
0(
0'
0&
0%
0$
0#
b0 "
0!
$end
#5000
1(
#10000
0(
#15000
1(
#20000
0(
#25000
1(
#30000
0(
#35000
1(
#40000
0(
#45000
b1 =
1/
1(
#50000
0(
#55000
b10 =
1(
#60000
0(
#65000
b11 =
1(
#70000
0(
#75000
b100 =
1(
#80000
0(
#85000
b101 =
1(
#90000
0(
#95000
b110 =
1(
#100000
0(
#105000
b0 =
b1 <
1.
1*
1C
1?
1(
#110000
0(
#115000
b100000101010101010101000100111101011111010000110101010001010010010011000010000000100000 1
b1 :
1!
b1 "
b1 ;
1(
#120000
0(
#125000
1!
1(
#130000
0(
#135000
1!
1(
#140000
0(
#145000
1!
1(
#150000
0(
#155000
1'
1#
0!
12
0*
1E
0?
1(
#160000
0(
#165000
1'
1#
1(
#170000
0(
#175000
1'
1#
1(
#180000
0(
#185000
1'
1#
1(
#190000
0(
#195000
1'
1#
1(
#200000
0(
#205000
1!
1'
1#
1*
1?
1(
#210000
0(
#215000
1'
1#
1!
1(
#220000
0(
#225000
1'
1#
1!
1(
#230000
0(
#235000
1'
1#
1!
1(
#240000
0(
#245000
1'
1#
1!
1(
#250000
0(
#255000
b1 =
0'
0#
0!
b10 <
10
02
0.
0*
1D
0E
0C
0?
1(
#260000
0(
#265000
b101001101000101010000110101010101010010010010010101010001011001001000000010000000100000 1
1!
b10 "
b10 ;
b10 =
b10 :
1(
#270000
0(
#275000
b11 =
1!
1(
#280000
0(
#285000
1!
b100 =
1(
#290000
0(
#295000
b101 =
1!
1(
#300000
0(
#305000
1%
1!
b110 =
b101 <
1)
1>
1(
#310000
0(
#315000
b100000101001100010000010101001001001101010111110101001101010100010000010101010001000101 1
b101 :
b111 =
1&
b101 "
b101 ;
1%
1!
1(
#320000
0(
#325000
1&
1%
1!
b1000 =
1(
#330000
0(
#335000
b1001 =
1&
1%
1!
1(
#340000
0(
#345000
1&
1%
1!
b1010 =
1(
#350000
0(
#355000
b1011 =
1&
1%
1!
b0 <
00
0)
0D
0>
1(
#360000
0(
#365000
b100100101000100010011000100010100100000001000000010000000100000001000000010000000100000 1
b0 "
b0 ;
0&
0%
0!
b1100 =
b0 :
1(
#370000
0(
#375000
b1101 =
1(
#380000
0(
#385000
b1110 =
1(
#390000
0(
#395000
b1111 =
1(
#400000
0(
#405000
b10000 =
b100 <
1-
1B
1(
#410000
0(
#415000
b100110101000001010011100101010101000001010011000101111101001111010101100101001000100000 1
b100 :
b10001 =
1!
b100 "
b100 ;
1(
#420000
0(
#425000
1!
b10010 =
1(
#430000
0(
#435000
b10011 =
1!
1(
#440000
0(
#445000
1!
b10100 =
1(
#450000
0(
#455000
b10101 =
1'
1#
0!
1+
1,
0-
1@
1A
0B
1(
#460000
0(
#465000
1'
1#
b10110 =
1(
#470000
0(
#475000
b10111 =
1'
1#
1(
#480000
0(
#485000
1'
1#
b11000 =
1(
#490000
0(
#495000
b11001 =
1'
1#
1(
#500000
0(
#505000
1!
1'
1#
b11010 =
1-
1B
1(
#510000
0(
#515000
b11011 =
1'
1#
1!
1(
#520000
0(
#525000
1'
1#
1!
b11100 =
1(
#530000
0(
#535000
b11101 =
1'
1#
1!
1(
#540000
0(
#545000
1'
1#
1!
b11110 =
1(
#550000
0(
#555000
b11111 =
0'
0#
0!
b0 <
0+
0,
0-
0@
0A
0B
1(
#560000
0(
#565000
b100100101000100010011000100010100100000001000000010000000100000001000000010000000100000 1
b0 "
b0 ;
b100000 =
b0 :
1(
#570000
0(
#575000
b100001 =
1(
#580000
0(
#585000
b100010 =
1(
#590000
0(
#595000
b100011 =
1(
#600000
0(
#605000
b0 =
b1 <
12
1.
1*
b11 F
1E
1C
1?
1(
#610000
0(
#615000
b100000101010101010101000100111101011111010000110101010001010010010011000010000000100000 1
b1 :
1'
1#
1!
b1 "
b1 ;
1(
#620000
0(
#625000
1'
1#
1!
1(
#630000
0(
#635000
b1 =
0'
1#
0!
0.
0*
b11010010 F
0C
0?
1(
#640000
0(
#645000
1#
b10 =
1(
#650000
0(
#655000
b11 =
1#
1(
#660000
0(
#665000
1#
b100 =
1(
#670000
0(
#675000
b101 =
1#
1(
#680000
0(
#685000
1#
b110 =
1(
#690000
0(
#695000
b111 =
1#
1(
#700000
0(
#705000
1#
b1000 =
1(
#710000
0(
#715000
b1001 =
1#
1(
#720000
0(
#725000
1#
b1010 =
1(
#730000
0(
#735000
b1011 =
1#
1(
#740000
0(
#745000
1#
b1100 =
1(
#750000
0(
#755000
b1101 =
1#
1(
#760000
0(
#765000
1#
b1110 =
1(
#770000
0(
#775000
b1111 =
1#
1(
#780000
0(
#785000
1#
b10000 =
1(
#790000
0(
#795000
b10001 =
1#
1(
#800000
0(
#805000
1#
b10010 =
1(
#810000
0(
#815000
b10011 =
1#
1(
#820000
0(
#825000
1#
b10100 =
1(
#830000
0(
#835000
b10101 =
1#
1(
#840000
0(
#845000
1#
b10110 =
1(
#850000
0(
#855000
b10111 =
1#
1(
#860000
0(
#865000
1#
b11000 =
1(
#870000
0(
#875000
b11001 =
1#
1(
#880000
0(
#885000
1#
b11010 =
1(
#890000
0(
#895000
b11011 =
1#
1(
#900000
0(
#905000
1#
b11100 =
1(
#910000
0(
#915000
b11101 =
1#
1(
#920000
0(
#925000
1#
b11110 =
1(
#930000
0(
#935000
b11111 =
1#
1(
#940000
0(
#945000
1#
b100000 =
1(
#950000
0(
#955000
b100001 =
1#
1(
#960000
0(
#965000
1#
b100010 =
1(
#970000
0(
#975000
b100011 =
1#
1(
#980000
0(
#985000
1#
b100100 =
1(
#990000
0(
#995000
b100101 =
1#
1(
#1000000
0(
#1005000
1#
b100110 =
1(
#1010000
0(
#1015000
b100111 =
1#
1(
#1020000
0(
#1025000
1#
b101000 =
1(
#1030000
0(
#1035000
b101001 =
1#
1(
#1040000
0(
#1045000
1#
b101010 =
1(
#1050000
0(
#1055000
b101011 =
1#
1(
#1060000
0(
#1065000
1#
b101100 =
1(
#1070000
0(
#1075000
b101101 =
1#
1(
#1080000
0(
#1085000
1#
b101110 =
1(
#1090000
0(
#1095000
b101111 =
1#
1(
#1100000
0(
#1105000
1#
b110000 =
1(
#1110000
0(
#1115000
b110001 =
1#
1(
#1120000
0(
#1125000
1#
b110010 =
1(
#1130000
0(
#1135000
b110011 =
1#
1(
#1140000
0(
#1145000
1#
b110100 =
1(
#1150000
0(
#1155000
b110101 =
1#
1(
#1160000
0(
#1165000
1#
b110110 =
1(
#1170000
0(
#1175000
b110111 =
1#
1(
#1180000
0(
#1185000
1#
b111000 =
1(
#1190000
0(
#1195000
b111001 =
1#
1(
#1200000
0(
#1205000
1#
b111010 =
1(
#1210000
0(
#1215000
b111011 =
1#
1(
#1220000
0(
#1225000
1#
b111100 =
1(
#1230000
0(
#1235000
b111101 =
1#
1(
#1240000
0(
#1245000
1#
b111110 =
1(
#1250000
0(
#1255000
b111111 =
1#
1(
#1260000
0(
#1265000
1#
b1000000 =
1(
#1270000
0(
#1275000
b1000001 =
1#
1(
#1280000
0(
#1285000
1#
b1000010 =
1(
#1290000
0(
#1295000
b1000011 =
1#
1(
#1300000
0(
#1305000
1#
b1000100 =
1(
#1310000
0(
#1315000
b1000101 =
1#
1(
#1320000
0(
#1325000
1#
b1000110 =
1(
#1330000
0(
#1335000
b1000111 =
1#
1(
#1340000
0(
#1345000
1#
b1001000 =
1(
#1350000
0(
#1355000
b1001001 =
1#
1(
#1360000
0(
#1365000
1#
b1001010 =
1(
#1370000
0(
#1375000
b1001011 =
1#
1(
#1380000
0(
#1385000
1#
b1001100 =
1(
#1390000
0(
#1395000
b1001101 =
1#
1(
#1400000
0(
#1405000
1#
b1001110 =
1(
#1410000
0(
#1415000
b1001111 =
1#
1(
#1420000
0(
#1425000
1#
b1010000 =
1(
#1430000
0(
#1435000
b1010001 =
1#
1(
#1440000
0(
#1445000
1#
b1010010 =
1(
#1450000
0(
#1455000
b1010011 =
1#
1(
#1460000
0(
#1465000
1#
b1010100 =
1(
#1470000
0(
#1475000
b1010101 =
1#
1(
#1480000
0(
#1485000
1#
b1010110 =
1(
#1490000
0(
#1495000
b1010111 =
1#
1(
#1500000
0(
#1505000
1#
b1011000 =
1(
#1510000
0(
#1515000
b1011001 =
1#
1(
#1520000
0(
#1525000
1#
b1011010 =
1(
#1530000
0(
#1535000
b1011011 =
1#
1(
#1540000
0(
#1545000
1#
b1011100 =
1(
#1550000
0(
#1555000
b1011101 =
1#
1(
#1560000
0(
#1565000
1#
b1011110 =
1(
#1570000
0(
#1575000
b1011111 =
1#
1(
#1580000
0(
#1585000
1#
b1100000 =
1(
#1590000
0(
#1595000
b1100001 =
1#
1(
#1600000
0(
#1605000
1#
b1100010 =
1(
#1610000
0(
#1615000
b1100011 =
1#
1(
#1620000
0(
#1625000
1#
b1100100 =
1(
#1630000
0(
#1635000
b1100101 =
1#
1(
#1640000
0(
#1645000
1#
b1100110 =
1(
#1650000
0(
#1655000
b1100111 =
1#
1(
#1660000
0(
#1665000
1#
b1101000 =
1(
#1670000
0(
#1675000
b1101001 =
1#
1(
#1680000
0(
#1685000
1#
b1101010 =
1(
#1690000
0(
#1695000
b1101011 =
1#
1(
#1700000
0(
#1705000
1#
b1101100 =
1(
#1710000
0(
#1715000
b1101101 =
1#
1(
#1720000
0(
#1725000
1#
b1101110 =
1(
#1730000
0(
#1735000
b1101111 =
1#
1(
#1740000
0(
#1745000
1#
b1110000 =
1(
#1750000
0(
#1755000
b1110001 =
1#
1(
#1760000
0(
#1765000
1#
b1110010 =
1(
#1770000
0(
#1775000
b1110011 =
1#
1(
#1780000
0(
#1785000
1#
b1110100 =
1(
#1790000
0(
#1795000
b1110101 =
1#
1(
#1800000
0(
#1805000
1#
b1110110 =
1(
#1810000
0(
#1815000
b1110111 =
1#
1(
#1820000
0(
#1825000
1#
b1111000 =
1(
#1830000
0(
#1835000
b1111001 =
1#
1(
#1840000
0(
#1845000
1#
b1111010 =
1(
#1850000
0(
#1855000
b1111011 =
1#
1(
#1860000
0(
#1865000
1#
b1111100 =
1(
#1870000
0(
#1875000
b1111101 =
1#
1(
#1880000
0(
#1885000
1#
b1111110 =
1(
#1890000
0(
#1895000
b1111111 =
1#
1(
#1900000
0(
#1905000
1#
b10000000 =
1(
#1910000
0(
#1915000
b10000001 =
1#
1(
#1920000
0(
#1925000
1#
b10000010 =
1(
#1930000
0(
#1935000
b10000011 =
1#
1(
#1940000
0(
#1945000
1#
b10000100 =
1(
#1950000
0(
#1955000
b10000101 =
1#
1(
#1960000
0(
#1965000
1#
b10000110 =
1(
#1970000
0(
#1975000
b10000111 =
1#
1(
#1980000
0(
#1985000
1#
b10001000 =
1(
#1990000
0(
#1995000
b10001001 =
1#
1(
#2000000
0(
#2005000
1#
b10001010 =
1(
#2010000
0(
#2015000
b10001011 =
1#
1(
#2020000
0(
#2025000
1#
b10001100 =
1(
#2030000
0(
#2035000
b10001101 =
1#
1(
#2040000
0(
#2045000
1#
b10001110 =
1(
#2050000
0(
#2055000
b10001111 =
1#
1(
#2060000
0(
#2065000
1#
b10010000 =
1(
#2070000
0(
#2075000
b10010001 =
1#
1(
#2080000
0(
#2085000
1#
b10010010 =
1(
#2090000
0(
#2095000
b10010011 =
1#
1(
#2100000
0(
#2105000
1#
b10010100 =
1(
#2110000
0(
#2115000
b10010101 =
1#
1(
#2120000
0(
#2125000
1#
b10010110 =
1(
#2130000
0(
#2135000
b10010111 =
1#
1(
#2140000
0(
#2145000
1#
b10011000 =
1(
#2150000
0(
#2155000
b10011001 =
1#
1(
#2160000
0(
#2165000
1#
b10011010 =
1(
#2170000
0(
#2175000
b10011011 =
1#
1(
#2180000
0(
#2185000
1#
b10011100 =
1(
#2190000
0(
#2195000
b10011101 =
1#
1(
#2200000
0(
#2205000
1#
b10011110 =
1(
#2210000
0(
#2215000
b10011111 =
1#
1(
#2220000
0(
#2225000
1#
b10100000 =
1(
#2230000
0(
#2235000
b10100001 =
1#
1(
#2240000
0(
#2245000
1#
b10100010 =
1(
#2250000
0(
#2255000
b10100011 =
1#
1(
#2260000
0(
#2265000
1#
b10100100 =
1(
#2270000
0(
#2275000
b10100101 =
1#
1(
#2280000
0(
#2285000
1#
b10100110 =
1(
#2290000
0(
#2295000
b10100111 =
1#
1(
#2300000
0(
#2305000
1#
b10101000 =
1(
#2310000
0(
#2315000
b10101001 =
1#
1(
#2320000
0(
#2325000
1#
b10101010 =
1(
#2330000
0(
#2335000
b10101011 =
1#
1(
#2340000
0(
#2345000
1#
b10101100 =
1(
#2350000
0(
#2355000
b10101101 =
1#
1(
#2360000
0(
#2365000
1#
b10101110 =
1(
#2370000
0(
#2375000
b10101111 =
1#
1(
#2380000
0(
